MANIFEST.in
README.md
pyproject.toml
setup.py
version.txt
wiser/__init__.py
wiser/gcloud/__init__.py
wiser/gcloud/storage/__init__.py
wiser/gcloud/storage/connectors/__init__.py
wiser/gcloud/storage/connectors/storage_connector.py
wiser/gcloud/storage/services/__init__.py
wiser/gcloud/storage/services/storage_service.py
wiser/gcloud/storage/types/__init__.py
wiser/gcloud/storage/types/location.py
wiser_gcloud_storage.egg-info/PKG-INFO
wiser_gcloud_storage.egg-info/SOURCES.txt
wiser_gcloud_storage.egg-info/dependency_links.txt
wiser_gcloud_storage.egg-info/namespace_packages.txt
wiser_gcloud_storage.egg-info/not-zip-safe
wiser_gcloud_storage.egg-info/requires.txt
wiser_gcloud_storage.egg-info/top_level.txt