Metadata-Version: 2.1
Name: wiser-gcloud-storage
Version: 1.1.1
Summary: Google Cloud Storage APIs for wiser
Home-page: https://github.com/audax-tech/wiser-gcloud-storage
Author: Nicola Massarenti
Author-email: nicola.massarenti@gmail.com
License: UNKNOWN
Project-URL: Bug Tracker, https://github.com/audax-tech/wiser-gcloud-storage/issues
Platform: Posix; MacOS X; Windows
Classifier: Programming Language :: Python :: 3.8
Classifier: License :: OSI Approved :: MIT License
Classifier: Operating System :: OS Independent
Requires-Python: >=3.8
